AndyPy/__init__.py
AndyPy/util.py
AndyPy/tool/__init__.py
AndyPy/tool/cv.py
AndyPy/tool/excel2csv.py
AndyPy/tool/pics2pdf.py
AndyPy-1.5.dist-info/METADATA
AndyPy-1.5.dist-info/WHEEL
AndyPy-1.5.dist-info/top_level.txt
AndyPy-1.5.dist-info/RECORD
