Metadata-Version: 2.1
Name: AndyPy
Version: 1.5
Summary: 封装各类常用的功能，便于一句代码调用。util为通用工具，tool为特定业务工具。Andy:597966823
Home-page: UNKNOWN
Author: Andy
Author-email: 597966823@qq.com
License: UNKNOWN
Platform: UNKNOWN
